scrollshot2pdf.py
scrollshot2pdf-0.1.1.dist-info/METADATA
scrollshot2pdf-0.1.1.dist-info/WHEEL
scrollshot2pdf-0.1.1.dist-info/entry_points.txt
scrollshot2pdf-0.1.1.dist-info/licenses/LICENSE
scrollshot2pdf-0.1.1.dist-info/RECORD
