Metadata-Version: 2.4
Name: scrollshot2pdf
Version: 0.1.1
Summary: Convert tall screenshots into multi-page PDFs
Project-URL: homepage, https://github.com/osteele/scrollshot2pdf
Project-URL: repository, https://github.com/osteele/scrollshot2pdf.git
Project-URL: issues, https://github.com/osteele/scrollshot2pdf/issues
Author-email: Oliver Steele <steele@osteele.com>
License: MIT
License-File: LICENSE
Keywords: pdf,screenshot,scrollshot
Requires-Python: >=3.10
Requires-Dist: pillow
Requires-Dist: reportlab
Provides-Extra: dev
Requires-Dist: pyright; extra == 'dev'
Requires-Dist: pytest; extra == 'dev'
Requires-Dist: pytest-cov; extra == 'dev'
Requires-Dist: ruff; extra == 'dev'
Provides-Extra: ocr
Requires-Dist: pytesseract; extra == 'ocr'
